setup.cfg
setup.py
src/scripts/mt2blogger.py
src/scripts/mt2blogger.py
src/typepad2blogger/__init__.py
src/typepad2blogger/blogger.py
src/typepad2blogger/mt.py
src/typepad2blogger.egg-info/PKG-INFO
src/typepad2blogger.egg-info/SOURCES.txt
src/typepad2blogger.egg-info/dependency_links.txt
src/typepad2blogger.egg-info/not-zip-safe
src/typepad2blogger.egg-info/requires.txt
src/typepad2blogger.egg-info/top_level.txt
src/typepad2blogger/test/__init__.py
src/typepad2blogger/test/test_mt.py