Metadata-Version: 1.0
Name: typepad2blogger
Version: 0.0.2
Summary: typepad2blogger - insert typepad exported entries (moveable type import/export) into blogger
Home-page: http://www.piratehaven.org/~epu/index#typepad2blogger
Author: Erik Purins
Author-email: erik@purins.com
License: http://www.gnu.org/licenses/gpl.txt
Platform: UNKNOWN
Classifier: Development Status :: 3 - Alpha
Classifier: Environment :: Console
Classifier: Intended Audience :: Developers
Classifier: License :: OSI Approved :: GNU General Public License (GPL)
Classifier: License :: OSI Approved :: GNU General Public License (GPL)
Classifier: Topic :: Utilities
